custom_imports/Install_server.py
custom_imports/Remove_server.py
custom_imports/Update_server.py
custom_imports/__init__.py
custom_imports/install_server2.py
custom_imports/jsontestn.py
custom_imports/rcon.py
custom_imports/scrape_website.py
custom_imports/start_service.py
factocli-0.3.4.data/scripts/factocli
factocli-0.3.4.dist-info/LICENSE
factocli-0.3.4.dist-info/METADATA
factocli-0.3.4.dist-info/WHEEL
factocli-0.3.4.dist-info/top_level.txt
factocli-0.3.4.dist-info/RECORD
