Metadata-Version: 2.1
Name: factocli
Version: 0.3.4
Summary: A Cli for managing a Factorio Headless Server
Home-page: https://github.com/Edris89/facto
Author: Edris Keyam
Author-email: edriskeyam82@hotmail.com
License: UNKNOWN
Platform: UNKNOWN
Classifier: Programming Language :: Python :: 3
Classifier: License :: OSI Approved :: MIT License
Classifier: Operating System :: OS Independent
Requires-Dist: PyInquirer
Requires-Dist: wget
Requires-Dist: termcolor
Requires-Dist: bs4
Requires-Dist: psutil
